coordinate_geomentry.py
coordinate_geomentry-1.2.dist-info/METADATA
coordinate_geomentry-1.2.dist-info/WHEEL
coordinate_geomentry-1.2.dist-info/top_level.txt
coordinate_geomentry-1.2.dist-info/RECORD
