Metadata-Version: 2.1
Name: coordinate-geomentry
Version: 1.2
Summary: coordinate geomentry formulae
Home-page: https://github.com/Sruthi213025/coordinate_geomentry.git
Author: Sruthi S
Author-email: sruthisugan3025@gmail.com
License: UNKNOWN
Platform: UNKNOWN
Classifier: Programming Language :: Python :: 3.5
Classifier: Programming Language :: Python :: 3.6
Classifier: Programming Language :: Python :: 3.7
Classifier: Programming Language :: Python :: 3.8
Classifier: Operating System :: OS Independent
